{
    "zacks": [
        {
            "symbol": "CLF",
            "pct_chg": 4.530918822490812,
            "date": "2023-01-09T18:01:19.891928",
            "score": 100,
            "start_price": 18.760000228881836,
            "end_price": 19.610000610351562
        },
        {
            "symbol": "NUE",
            "pct_chg": 11.998613143337757,
            "date": "2023-01-09T18:03:33.565082",
            "score": 100,
            "start_price": 145.10000610351562,
            "end_price": 162.50999450683594
        },
        {
            "symbol": "PERI",
            "pct_chg": 4.910708642221296,
            "date": "2023-01-09T18:03:47.094764",
            "score": 100,
            "start_price": 29.1200008392334,
            "end_price": 30.549999237060547
        },
        {
            "symbol": "RGA",
            "pct_chg": 3.266534770080459,
            "date": "2023-01-09T18:04:03.911531",
            "score": 100,
            "start_price": 145.72000122070312,
            "end_price": 150.47999572753906
        },
        {
            "symbol": "STLA",
            "pct_chg": 6.010227364122907,
            "date": "2023-01-09T18:04:31.572819",
            "score": 100,
            "start_price": 15.640000343322754,
            "end_price": 16.579999923706055
        },
        {
            "symbol": "AAL",
            "pct_chg": 15.15789366604989,
            "date": "2023-01-09T18:05:23.077823",
            "score": 100,
            "start_price": 14.25,
            "end_price": 16.40999984741211
        },
        {
            "symbol": "PAG",
            "pct_chg": 18.08746126479055,
            "date": "2023-01-09T18:05:32.075379",
            "score": 100,
            "start_price": 117.54000091552734,
            "end_price": 138.8000030517578
        },
        {
            "symbol": "VST",
            "pct_chg": 1.1607153272750603,
            "date": "2023-01-11T08:16:33.092790",
            "score": 100,
            "start_price": 22.399999618530273,
            "end_price": 22.65999984741211
        },
        {
            "symbol": "PRMW",
            "pct_chg": 1.7464392200720686,
            "date": "2023-01-12T08:15:05.095751",
            "score": 100,
            "start_price": 15.460000038146973,
            "end_price": 15.729999542236328
        },
        {
            "symbol": "NXST",
            "pct_chg": 5.825501141896522,
            "date": "2023-01-12T08:15:08.076459",
            "score": 100,
            "start_price": 185.22000122070312,
            "end_price": 196.00999450683594
        },
        {
            "symbol": "RCUS",
            "pct_chg": 10.922993218651431,
            "date": "2023-01-12T08:15:33.865464",
            "score": 100,
            "start_price": 18.309999465942383,
            "end_price": 20.309999465942383
        },
        {
            "symbol": "PFGC",
            "pct_chg": -0.5432931859664221,
            "date": "2023-01-11T08:17:08.130056",
            "score": 100,
            "start_price": 58.900001525878906,
            "end_price": 58.58000183105469
        },
        {
            "symbol": "ARHS",
            "pct_chg": 15.702475691157705,
            "date": "2023-01-11T08:17:28.189899",
            "score": 100,
            "start_price": 12.100000381469727,
            "end_price": 14.0
        },
        {
            "symbol": "WH",
            "pct_chg": 7.511083555822086,
            "date": "2023-01-12T08:17:15.670873",
            "score": 100,
            "start_price": 72.16000366210938,
            "end_price": 77.58000183105469
        },
        {
            "symbol": "JD",
            "pct_chg": -15.581543616554919,
            "date": "2023-01-11T12:28:08.418732",
            "score": 100,
            "start_price": 63.279998779296875,
            "end_price": 53.41999816894531
        },
        {
            "symbol": "EXPE",
            "pct_chg": 18.862690357375218,
            "date": "2023-01-10T08:14:35.752890",
            "score": 100,
            "start_price": 93.7300033569336,
            "end_price": 111.41000366210938
        },
        {
            "symbol": "NRG",
            "pct_chg": 6.161429625414581,
            "date": "2023-01-12T12:27:33.711457",
            "score": 100,
            "start_price": 32.459999084472656,
            "end_price": 34.459999084472656
        },
        {
            "symbol": "GWW",
            "pct_chg": 17.70887490545861,
            "date": "2023-01-10T08:14:58.322339",
            "score": 100,
            "start_price": 557.6300048828125,
            "end_price": 656.3800048828125
        },
        {
            "symbol": "JD",
            "pct_chg": -16.661467331372226,
            "date": "2023-01-10T08:15:56.118136",
            "score": 100,
            "start_price": 64.0999984741211,
            "end_price": 53.41999816894531
        },
        {
            "symbol": "LW",
            "pct_chg": -1.050081690138892,
            "date": "2023-01-10T08:16:01.480624",
            "score": 100,
            "start_price": 99.04000091552734,
            "end_price": 98.0
        },
        {
            "symbol": "LH",
            "pct_chg": -0.3242257789741329,
            "date": "2023-01-10T08:16:18.394252",
            "score": 100,
            "start_price": 243.66000366210938,
            "end_price": 242.8699951171875
        },
        {
            "symbol": "LNTH",
            "pct_chg": 21.357411478517427,
            "date": "2023-01-10T08:16:20.673900",
            "score": 100,
            "start_price": 48.18000030517578,
            "end_price": 58.470001220703125
        },
        {
            "symbol": "ACI",
            "pct_chg": -1.715340459525124,
            "date": "2023-01-12T08:09:32.425914",
            "score": 100,
            "start_price": 21.56999969482422,
            "end_price": 21.200000762939453
        },
        {
            "symbol": "CNM",
            "pct_chg": 1.3357942319525804,
            "date": "2023-01-12T08:10:40.693072",
            "score": 100,
            "start_price": 21.709999084472656,
            "end_price": 22.0
        },
        {
            "symbol": "URI",
            "pct_chg": 19.417419507582302,
            "date": "2023-01-10T08:18:55.160247",
            "score": 100,
            "start_price": 375.2300109863281,
            "end_price": 448.0899963378906
        },
        {
            "symbol": "VSH",
            "pct_chg": -7.347667616808868,
            "date": "2023-01-10T08:19:31.846577",
            "score": 100,
            "start_price": 22.31999969482422,
            "end_price": 20.68000030517578
        },
        {
            "symbol": "ADM",
            "pct_chg": -4.960317442649758,
            "date": "2023-01-10T08:19:42.400011",
            "score": 100,
            "start_price": 85.68000030517578,
            "end_price": 81.43000030517578
        },
        {
            "symbol": "RTO",
            "pct_chg": -4.884964574289757,
            "date": "2023-01-12T12:28:54.575609",
            "score": 100,
            "start_price": 31.729999542236328,
            "end_price": 30.18000030517578
        },
        {
            "symbol": "ACDC",
            "pct_chg": -18.279998779296875,
            "date": "2023-01-11T08:09:33.724706",
            "score": 100,
            "start_price": 25.0,
            "end_price": 20.43000030517578
        },
        {
            "symbol": "BAH",
            "pct_chg": -1.975233162685069,
            "date": "2023-01-11T08:09:56.035117",
            "score": 100,
            "start_price": 97.70999908447266,
            "end_price": 95.77999877929688
        },
        {
            "symbol": "EVBG",
            "pct_chg": 14.690453796864636,
            "date": "2023-01-11T08:11:32.848873",
            "score": 100,
            "start_price": 28.59000015258789,
            "end_price": 32.790000915527344
        },
        {
            "symbol": "HOG",
            "pct_chg": 7.974481769588458,
            "date": "2023-01-11T08:12:25.612242",
            "score": 100,
            "start_price": 43.88999938964844,
            "end_price": 47.38999938964844
        },
        {
            "symbol": "HGV",
            "pct_chg": 9.054468678151176,
            "date": "2023-01-11T08:12:41.657226",
            "score": 100,
            "start_price": 42.40999984741211,
            "end_price": 46.25
        },
        {
            "symbol": "JKS",
            "pct_chg": -8.759893889009149,
            "date": "2023-01-12T08:13:19.849827",
            "score": 100,
            "start_price": 56.849998474121094,
            "end_price": 51.869998931884766
        },
        {
            "symbol": "LNTH",
            "pct_chg": 16.35821138448383,
            "date": "2023-01-12T08:13:55.757222",
            "score": 100,
            "start_price": 50.25,
            "end_price": 58.470001220703125
        },
        {
            "symbol": "LRN",
            "pct_chg": 0.3658573801924543,
            "date": "2023-01-29T02:05:24.191897",
            "score": 100,
            "start_price": 41.0,
            "end_price": 41.150001525878906
        },
        {
            "symbol": "CLVT",
            "pct_chg": -0.7366475712259063,
            "date": "2023-01-29T01:57:51.972412",
            "score": 100,
            "start_price": 10.859999656677246,
            "end_price": 10.779999732971191
        },
        {
            "symbol": "TGLS",
            "pct_chg": 2.6923073016354557,
            "date": "2023-01-29T02:02:42.365243",
            "score": 100,
            "start_price": 33.79999923706055,
            "end_price": 34.709999084472656
        },
        {
            "symbol": "EVBG",
            "pct_chg": 2.436746750684554,
            "date": "2023-01-29T02:03:52.293008",
            "score": 100,
            "start_price": 32.0099983215332,
            "end_price": 32.790000915527344
        },
        {
            "symbol": "HAL",
            "pct_chg": -5.273629083706887,
            "date": "2023-01-29T02:04:23.408833",
            "score": 100,
            "start_price": 40.20000076293945,
            "end_price": 38.08000183105469
        },
        {
            "symbol": "XRX",
            "pct_chg": -1.4457817204996657,
            "date": "2023-01-29T02:08:20.763172",
            "score": 100,
            "start_price": 16.600000381469727,
            "end_price": 16.360000610351562
        },
        {
            "symbol": "SUZ",
            "pct_chg": -1.7777760823567708,
            "date": "2023-01-30T16:24:04.178301",
            "score": 100,
            "start_price": 9.0,
            "end_price": 8.84000015258789
        },
        {
            "symbol": "ASAI",
            "pct_chg": -14.839967258724801,
            "date": "2023-01-30T16:31:48.390079",
            "score": 100,
            "start_price": 20.6200008392334,
            "end_price": 17.559999465942383
        },
        {
            "symbol": "URI",
            "pct_chg": 4.049692949861812,
            "date": "2023-01-30T16:32:03.380993",
            "score": 100,
            "start_price": 430.6499938964844,
            "end_price": 448.0899963378906
        },
        {
            "symbol": "CPA",
            "pct_chg": 0.8111148410373263,
            "date": "2023-01-30T16:32:07.655201",
            "score": 100,
            "start_price": 90.0,
            "end_price": 90.7300033569336
        },
        {
            "symbol": "EXPE",
            "pct_chg": -5.360174560959847,
            "date": "2023-01-27T05:31:37.436953",
            "score": 100,
            "start_price": 117.72000122070312,
            "end_price": 111.41000366210938
        },
        {
            "symbol": "BTU",
            "pct_chg": -7.010534896615541,
            "date": "2023-01-31T08:40:04.214747",
            "score": 100,
            "start_price": 27.530000686645508,
            "end_price": 25.600000381469727
        },
        {
            "symbol": "HP",
            "pct_chg": -13.077379164826125,
            "date": "2023-01-27T05:18:06.457810",
            "score": 100,
            "start_price": 50.0099983215332,
            "end_price": 43.470001220703125
        },
        {
            "symbol": "ET",
            "pct_chg": -5.122498295316044,
            "date": "2023-01-27T05:52:19.626553",
            "score": 100,
            "start_price": 13.470000267028809,
            "end_price": 12.779999732971191
        },
        {
            "symbol": "CLVT",
            "pct_chg": 0.2790672834529433,
            "date": "2023-01-27T08:47:45.095387",
            "score": 100,
            "start_price": 10.75,
            "end_price": 10.779999732971191
        },
        {
            "symbol": "SUN",
            "pct_chg": 0.06477818701637222,
            "date": "2023-01-27T05:51:20.857902",
            "score": 100,
            "start_price": 46.310001373291016,
            "end_price": 46.34000015258789
        },
        {
            "symbol": "COLL",
            "pct_chg": -7.873744237845514,
            "date": "2023-01-27T05:51:43.413980",
            "score": 100,
            "start_price": 28.829999923706055,
            "end_price": 26.559999465942383
        },
        {
            "symbol": "NTES",
            "pct_chg": -4.431620053478868,
            "date": "2023-01-27T08:47:47.548430",
            "score": 100,
            "start_price": 91.83999633789062,
            "end_price": 87.7699966430664
        },
        {
            "symbol": "ETD",
            "pct_chg": 9.336332073472471,
            "date": "2023-01-27T08:50:58.883278",
            "score": 100,
            "start_price": 26.670000076293945,
            "end_price": 29.15999984741211
        },
        {
            "symbol": "GPK",
            "pct_chg": -1.9789444772820723,
            "date": "2023-01-27T08:51:35.728397",
            "score": 100,
            "start_price": 23.75,
            "end_price": 23.280000686645508
        },
        {
            "symbol": "TGLS",
            "pct_chg": 2.6923073016354557,
            "date": "2023-01-27T08:51:37.273856",
            "score": 100,
            "start_price": 33.79999923706055,
            "end_price": 34.709999084472656
        },
        {
            "symbol": "BAP",
            "pct_chg": -0.44424090711267994,
            "date": "2023-01-31T08:40:29.081070",
            "score": 100,
            "start_price": 132.80999755859375,
            "end_price": 132.22000122070312
        },
        {
            "symbol": "CNM",
            "pct_chg": 3.920642044000199,
            "date": "2023-01-27T08:54:10.173286",
            "score": 100,
            "start_price": 21.170000076293945,
            "end_price": 22.0
        },
        {
            "symbol": "VIPS",
            "pct_chg": -10.28391214644105,
            "date": "2023-01-27T08:54:11.634223",
            "score": 100,
            "start_price": 15.850000381469727,
            "end_price": 14.220000267028809
        },
        {
            "symbol": "CPRX",
            "pct_chg": -3.125,
            "date": "2023-01-27T18:19:19.620785",
            "score": 100,
            "start_price": 16.0,
            "end_price": 15.5
        },
        {
            "symbol": "AXS",
            "pct_chg": 1.4045895477415777,
            "date": "2023-01-31T08:41:32.462211",
            "score": 100,
            "start_price": 61.939998626708984,
            "end_price": 62.810001373291016
        },
        {
            "symbol": "TGLS",
            "pct_chg": 2.9054241195858412,
            "date": "2023-01-31T08:45:09.806975",
            "score": 100,
            "start_price": 33.72999954223633,
            "end_price": 34.709999084472656
        },
        {
            "symbol": "HCC",
            "pct_chg": 0.4013955851385433,
            "date": "2023-01-31T08:47:20.505864",
            "score": 100,
            "start_price": 37.369998931884766,
            "end_price": 37.52000045776367
        },
        {
            "symbol": "ASC",
            "pct_chg": 21.299630139633063,
            "date": "2023-01-31T08:48:25.762973",
            "score": 100,
            "start_price": 13.850000381469727,
            "end_price": 16.799999237060547
        },
        {
            "symbol": "ADM",
            "pct_chg": -0.1593884959652887,
            "date": "2023-01-31T08:45:35.680177",
            "score": 100,
            "start_price": 81.55999755859375,
            "end_price": 81.43000030517578
        },
        {
            "symbol": "SMCI",
            "pct_chg": 19.444444444444446,
            "date": "2023-02-01T08:40:22.443262",
            "score": 100,
            "start_price": 72.0,
            "end_price": 86.0
        },
        {
            "symbol": "CLVT",
            "pct_chg": -3.231603224925793,
            "date": "2023-02-01T08:43:38.971389",
            "score": 100,
            "start_price": 11.140000343322754,
            "end_price": 10.779999732971191
        },
        {
            "symbol": "ASAI",
            "pct_chg": -8.541673082444149,
            "date": "2023-02-01T08:46:23.749327",
            "score": 100,
            "start_price": 19.200000762939453,
            "end_price": 17.559999465942383
        },
        {
            "symbol": "ARCH",
            "pct_chg": -5.092494030441209,
            "date": "2023-02-01T08:43:57.468309",
            "score": 100,
            "start_price": 148.64999389648438,
            "end_price": 141.0800018310547
        },
        {
            "symbol": "PHG",
            "pct_chg": -3.126814714614487,
            "date": "2023-02-01T08:44:56.491929",
            "score": 100,
            "start_price": 17.270000457763672,
            "end_price": 16.729999542236328
        },
        {
            "symbol": "EXPE",
            "pct_chg": -2.2290419957505714,
            "date": "2023-02-01T15:04:44.770479",
            "score": 100,
            "start_price": 113.94999694824219,
            "end_price": 111.41000366210938
        },
        {
            "symbol": "HP",
            "pct_chg": -7.194703076230828,
            "date": "2023-02-02T15:14:11.205901",
            "score": 100,
            "start_price": 46.84000015258789,
            "end_price": 43.470001220703125
        },
        {
            "symbol": "MUSA",
            "pct_chg": 2.56976933442345,
            "date": "2023-02-02T08:05:52.557796",
            "score": 100,
            "start_price": 258.0,
            "end_price": 264.6300048828125
        },
        {
            "symbol": "RYAAY",
            "pct_chg": -2.6651203741320693,
            "date": "2023-02-02T08:10:16.450378",
            "score": 100,
            "start_price": 94.93000030517578,
            "end_price": 92.4000015258789
        },
        {
            "symbol": "BAP",
            "pct_chg": -2.073769043961517,
            "date": "2023-02-02T08:10:24.147263",
            "score": 100,
            "start_price": 135.02000427246094,
            "end_price": 132.22000122070312
        },
        {
            "symbol": "CPRX",
            "pct_chg": 1.639344262295082,
            "date": "2023-02-02T15:15:11.996293",
            "score": 100,
            "start_price": 15.25,
            "end_price": 15.5
        },
        {
            "symbol": "RNR",
            "pct_chg": 5.933258483853012,
            "date": "2023-02-02T16:11:26.580051",
            "score": 100,
            "start_price": 209.16000366210938,
            "end_price": 221.57000732421875
        },
        {
            "symbol": "CNM",
            "pct_chg": -2.4822671950315596,
            "date": "2023-02-02T15:11:40.028249",
            "score": 100,
            "start_price": 22.559999465942383,
            "end_price": 22.0
        },
        {
            "symbol": "CPA",
            "pct_chg": -1.003816861569321,
            "date": "2023-02-03T16:07:23.094788",
            "score": 100,
            "start_price": 91.6500015258789,
            "end_price": 90.7300033569336
        },
        {
            "symbol": "YPF",
            "pct_chg": 1.5097697410156006,
            "date": "2023-02-03T08:10:13.430893",
            "score": 100,
            "start_price": 11.260000228881836,
            "end_price": 11.430000305175781
        },
        {
            "symbol": "PARR",
            "pct_chg": 4.465649016121173,
            "date": "2023-02-07T08:06:28.601423",
            "score": 100,
            "start_price": 26.200000762939453,
            "end_price": 27.3700008392334
        },
        {
            "symbol": "MTCH",
            "pct_chg": -8.717845278036975,
            "date": "2023-02-03T08:11:43.194048",
            "score": 100,
            "start_price": 50.93000030517578,
            "end_price": 46.4900016784668
        },
        {
            "symbol": "ARLP",
            "pct_chg": -6.000001695421007,
            "date": "2023-02-03T08:12:01.080399",
            "score": 100,
            "start_price": 22.5,
            "end_price": 21.149999618530273
        },
        {
            "symbol": "JD",
            "pct_chg": -8.97938418994164,
            "date": "2023-02-03T08:12:53.825593",
            "score": 100,
            "start_price": 58.689998626708984,
            "end_price": 53.41999816894531
        },
        {
            "symbol": "CRH",
            "pct_chg": -2.1099699539732204,
            "date": "2023-02-05T00:11:03.122241",
            "score": 100,
            "start_price": 46.91999816894531,
            "end_price": 45.93000030517578
        },
        {
            "symbol": "SUN",
            "pct_chg": -1.8636193252138396,
            "date": "2023-02-05T00:15:54.334145",
            "score": 100,
            "start_price": 47.220001220703125,
            "end_price": 46.34000015258789
        },
        {
            "symbol": "ORAN",
            "pct_chg": -0.38647304713767794,
            "date": "2023-02-05T00:25:18.296232",
            "score": 100,
            "start_price": 10.350000381469727,
            "end_price": 10.3100004196167
        },
        {
            "symbol": "UBS",
            "pct_chg": 1.0772812090249484,
            "date": "2023-02-05T00:36:16.734213",
            "score": 100,
            "start_price": 21.350000381469727,
            "end_price": 21.579999923706055
        },
        {
            "symbol": "WNC",
            "pct_chg": -6.412890746467971,
            "date": "2023-02-06T14:08:55.182016",
            "score": 100,
            "start_price": 29.15999984741211,
            "end_price": 27.290000915527344
        },
        {
            "symbol": "MOD",
            "pct_chg": -2.3076881067600103,
            "date": "2023-02-07T08:10:55.836127",
            "score": 100,
            "start_price": 23.399999618530273,
            "end_price": 22.860000610351562
        },
        {
            "symbol": "GWW",
            "pct_chg": -1.8056708959233958,
            "date": "2023-02-07T08:09:50.579004",
            "score": 100,
            "start_price": 668.4500122070312,
            "end_price": 656.3800048828125
        },
        {
            "symbol": "ARLP",
            "pct_chg": 0.7142838977632069,
            "date": "2023-02-09T16:08:52.075052",
            "score": 100,
            "start_price": 21.0,
            "end_price": 21.149999618530273
        },
        {
            "symbol": "UBS",
            "pct_chg": 0.7940218472934446,
            "date": "2023-02-07T08:11:34.297155",
            "score": 100,
            "start_price": 21.40999984741211,
            "end_price": 21.579999923706055
        },
        {
            "symbol": "ARLP",
            "pct_chg": -2.444652579266698,
            "date": "2023-02-07T16:06:25.416104",
            "score": 100,
            "start_price": 21.68000030517578,
            "end_price": 21.149999618530273
        },
        {
            "symbol": "PBF",
            "pct_chg": 0.49443945405977613,
            "date": "2023-02-08T08:14:11.177928",
            "score": 100,
            "start_price": 40.45000076293945,
            "end_price": 40.650001525878906
        },
        {
            "symbol": "MCHP",
            "pct_chg": -2.0158510406495957,
            "date": "2023-02-08T08:10:37.104566",
            "score": 100,
            "start_price": 85.81999969482422,
            "end_price": 84.08999633789062
        },
        {
            "symbol": "GPK",
            "pct_chg": 4.114490389897536,
            "date": "2023-02-08T08:10:46.807028",
            "score": 100,
            "start_price": 22.360000610351562,
            "end_price": 23.280000686645508
        },
        {
            "symbol": "SIGI",
            "pct_chg": -1.3015181607727548,
            "date": "2023-02-08T08:11:12.093643",
            "score": 100,
            "start_price": 101.41999816894531,
            "end_price": 100.0999984741211
        },
        {
            "symbol": "TT",
            "pct_chg": 1.8332703716858734,
            "date": "2023-02-08T08:12:42.132280",
            "score": 100,
            "start_price": 178.3699951171875,
            "end_price": 181.63999938964844
        },
        {
            "symbol": "COLL",
            "pct_chg": -3.207000914679307,
            "date": "2023-02-08T16:12:48.133002",
            "score": 100,
            "start_price": 27.440000534057617,
            "end_price": 26.559999465942383
        },
        {
            "symbol": "CLF",
            "pct_chg": -2.096855026939513,
            "date": "2023-02-08T16:14:51.303641",
            "score": 100,
            "start_price": 20.030000686645508,
            "end_price": 19.610000610351562
        },
        {
            "symbol": "ATI",
            "pct_chg": -3.651112263816889,
            "date": "2023-02-08T16:15:17.213244",
            "score": 100,
            "start_price": 39.439998626708984,
            "end_price": 38.0
        },
        {
            "symbol": "SKY",
            "pct_chg": -3.8341809178999218,
            "date": "2023-02-09T08:11:43.206530",
            "score": 100,
            "start_price": 70.68000030517578,
            "end_price": 67.97000122070312
        },
        {
            "symbol": "MCHP",
            "pct_chg": -2.44779661839024,
            "date": "2023-02-09T16:12:29.007626",
            "score": 100,
            "start_price": 86.19999694824219,
            "end_price": 84.08999633789062
        },
        {
            "symbol": "HAE",
            "pct_chg": 0.0,
            "date": "2023-02-10T08:09:21.632753",
            "score": 100,
            "start_price": 79.66999816894531,
            "end_price": 79.66999816894531
        },
        {
            "symbol": "RNR",
            "pct_chg": 1.3401060843165344,
            "date": "2023-02-09T16:10:43.841288",
            "score": 100,
            "start_price": 218.63999938964844,
            "end_price": 221.57000732421875
        },
        {
            "symbol": "CLVT",
            "pct_chg": 0.0,
            "date": "2023-02-10T08:09:24.974643",
            "score": 100,
            "start_price": 10.779999732971191,
            "end_price": 10.779999732971191
        },
        {
            "symbol": "ADM",
            "pct_chg": 0.0,
            "date": "2023-02-10T16:12:48.728289",
            "score": 100,
            "start_price": 81.43000030517578,
            "end_price": 81.43000030517578
        },
        {
            "symbol": "CNM",
            "pct_chg": 0.0,
            "date": "2023-02-10T16:11:13.273050",
            "score": 100,
            "start_price": 22.0,
            "end_price": 22.0
        }
    ],
    "thestreet": [
        {
            "symbol": "IEX",
            "pct_chg": -4.850191640449532,
            "date": "2023-01-31T08:01:46.002158",
            "score": 100,
            "start_price": 234.6300048828125,
            "end_price": 223.25
        },
        {
            "symbol": "CAT",
            "pct_chg": -1.2232796010744371,
            "date": "2023-02-02T08:01:02.771085",
            "score": 100,
            "start_price": 249.3300018310547,
            "end_price": 246.27999877929688
        },
        {
            "symbol": "PWR",
            "pct_chg": 1.5933329264322917,
            "date": "2023-01-26T04:01:30.675387",
            "score": 100,
            "start_price": 150.0,
            "end_price": 152.38999938964844
        },
        {
            "symbol": "PCAR",
            "pct_chg": -0.4693213653751369,
            "date": "2023-01-26T04:02:03.275749",
            "score": 100,
            "start_price": 73.86666870117188,
            "end_price": 73.5199966430664
        },
        {
            "symbol": "MA",
            "pct_chg": -1.4556095351199065,
            "date": "2023-01-26T04:02:14.808448",
            "score": 100,
            "start_price": 375.1000061035156,
            "end_price": 369.6400146484375
        },
        {
            "symbol": "APD",
            "pct_chg": -8.696896678785066,
            "date": "2023-01-28T09:37:23.062086",
            "score": 100,
            "start_price": 313.55999755859375,
            "end_price": 286.2900085449219
        },
        {
            "symbol": "TSCO",
            "pct_chg": 3.767229453553716,
            "date": "2023-01-28T09:37:33.698739",
            "score": 100,
            "start_price": 225.6300048828125,
            "end_price": 234.1300048828125
        },
        {
            "symbol": "LSTR",
            "pct_chg": 3.1432293016699586,
            "date": "2023-02-01T08:01:48.530440",
            "score": 100,
            "start_price": 173.07000732421875,
            "end_price": 178.50999450683594
        },
        {
            "symbol": "AME",
            "pct_chg": -0.8041224528833762,
            "date": "2023-02-02T08:01:20.989307",
            "score": 100,
            "start_price": 145.5,
            "end_price": 144.3300018310547
        },
        {
            "symbol": "CP",
            "pct_chg": -0.8292854290142633,
            "date": "2023-02-02T08:01:22.150369",
            "score": 100,
            "start_price": 78.37999725341797,
            "end_price": 77.7300033569336
        },
        {
            "symbol": "NVT",
            "pct_chg": -0.20089320116201811,
            "date": "2023-02-09T08:01:22.098370",
            "score": 100,
            "start_price": 44.79999923706055,
            "end_price": 44.709999084472656
        }
    ],
    "gurufocus": [
        {
            "symbol": "MKTX",
            "pct_chg": -5.709970370148538,
            "date": "2023-01-30T16:13:41.820304",
            "score": 100,
            "start_price": 370.92999267578125,
            "end_price": 349.75
        },
        {
            "symbol": "CHKP",
            "pct_chg": 1.017567986311123,
            "date": "2023-02-07T19:10:11.975420",
            "score": 100,
            "start_price": 125.79000091552734,
            "end_price": 127.06999969482422
        }
    ]
}